<?xml version="1.0" encoding="utf-8"?>
<BuildReasons>
  <Rule ID="$(AS_PROJECT_PATH)\temp\objects\modbusforignition\x20cp0482\modbus\modbus.st.c">
    <BuildReason>Prerequiste "$(AS_PROJECT_PATH)\logical\modbus\modbus.st" differs.
</BuildReason>
  </Rule>
  <Rule ID="$(AS_PROJECT_PATH)\temp\objects\modbusforignition\x20cp0482\modbus\modbus.st.o">
    <BuildReason>Prerequiste "$(AS_PROJECT_PATH)\temp\objects\modbusforignition\x20cp0482\modbus\modbus.st.c" differs.
</BuildReason>
  </Rule>
  <Rule ID="$(AS_PROJECT_PATH)\temp\objects\modbusforignition\x20cp0482\modbus\_bur_pvdef.st.c">
    <BuildReason>Prerequiste "$(AS_PROJECT_PATH)\temp\objects\modbusforignition\x20cp0482\modbus\modbus.st.o" differs.
</BuildReason>
  </Rule>
  <Rule ID="$(AS_PROJECT_PATH)\temp\objects\modbusforignition\x20cp0482\modbus\_bur_pvdef.st.o">
    <BuildReason>Prerequiste "$(AS_PROJECT_PATH)\temp\objects\modbusforignition\x20cp0482\modbus\_bur_pvdef.st.c" differs.
</BuildReason>
  </Rule>
  <Rule ID="$(AS_PROJECT_PATH)\temp\objects\modbusforignition\x20cp0482\modbus\a.out">
    <BuildReason>Prerequiste "$(AS_PROJECT_PATH)\temp\objects\modbusforignition\x20cp0482\modbus\modbus.st.o" differs.
</BuildReason>
  </Rule>
  <Rule ID="$(AS_PROJECT_PATH)\temp\objects\modbusforignition\x20cp0482\modbus\modbus.ox">
    <BuildReason>Prerequiste "$(AS_PROJECT_PATH)\temp\objects\modbusforignition\x20cp0482\modbus\a.out" differs.
</BuildReason>
  </Rule>
  <Rule ID="$(AS_PROJECT_PATH)\temp\objects\modbusforignition\x20cp0482\modbus.br">
    <BuildReason>Prerequiste "$(AS_PROJECT_PATH)\temp\objects\modbusforignition\x20cp0482\modbus\modbus.ox" differs.
</BuildReason>
  </Rule>
  <Rule ID="#cpu_tp.mak">
    <BuildReason>Rule is forced.</BuildReason>
  </Rule>
  <Rule ID="$(AS_PROJECT_PATH)\binaries\modbusforignition\x20cp0482\transfer.lst">
    <BuildReason>Prerequiste "$(AS_PROJECT_PATH)\temp\objects\modbusforignition\x20cp0482\modbus.br" differs.
</BuildReason>
  </Rule>
</BuildReasons>